document_inference/__init__.py
document_inference-0.0.2.dist-info/METADATA
document_inference-0.0.2.dist-info/WHEEL
document_inference-0.0.2.dist-info/top_level.txt
document_inference-0.0.2.dist-info/RECORD
